CHANGES.txt
COPYRIGHT.txt
LICENSE.txt
MANIFEST.in
README.rst
setup.py
src/githubbuildout/__init__.py
src/githubbuildout/githubbuildout.py
src/githubbuildout.egg-info/PKG-INFO
src/githubbuildout.egg-info/SOURCES.txt
src/githubbuildout.egg-info/dependency_links.txt
src/githubbuildout.egg-info/entry_points.txt
src/githubbuildout.egg-info/not-zip-safe
src/githubbuildout.egg-info/requires.txt
src/githubbuildout.egg-info/test_info.txt
src/githubbuildout.egg-info/top_level.txt