Metadata-Version: 1.1
Name: githubbuildout
Version: 0.1
Summary: Buildout extension to enable downloads from private GitHub repositories into buildout find-links and download recipes
Home-page: https://github.com/isolationism/githubbuildout
Author: Kevin Williams
Author-email: kevin@weblivion.com
License: ZPL 2.1
Keywords: buildout github private repository download
Platform: UNKNOWN
Classifier: Development Status :: 4 - Beta
Classifier: Intended Audience :: Developers
Classifier: License :: OSI Approved :: Zope Public License
Classifier: Framework :: Buildout :: Extension
Classifier: Topic :: Software Development :: Build Tools
